{
  "content": "Pokój do wynajęcia OD LUTEGO! Krzyki, świetny dojazd do centrum!!! WITAM!\n\nOferuję do wynajęcia dobrze wyposażone pokoje w mieszkaniu przy al. Armii Krajowej 34.\nPokoje zamykane na klucz, wyposażone są w: kanapę, szafę, regał, biurko, krzesło.\n\nW kuchni: meble w zabudowie, lodówka, mikrofalówka, płyta elektryczna oraz zestaw sztućcy, talerzy, itp.\n\nW łazience: pralka, prysznic, umywalka.\n\nOddzielne WC.\n\nNa wyposażeniu mieszkania znajdzie się również: żelazko, deska do prasowania, suszarka do ubrań, odkurzacz.\n\nInternet Wi-Fi w cenie.\n\nW pobliżu liczne linie tramwajowe i autobusowe, a także kilka marketów spożywczych;\n-8, 31, 32, 110, 125, 124, 134, 145, 146\n-Lidl, Biedronka, Kaufland, Żabka, Auchan, piekarnia\n\nPoniżej informacje dla zainteresowanych:\n- koszt najmu pokoju wynosi 750 zł + opłaty za media 150 zł/m-c (prąd, woda, ogrzewanie).\n\n- umowa podpisywana jest na czas określony do 31 sierpnia 2019 r. z możliwością przedłużenia,\n\n- w momencie podpisywania umowy pobierana jest kaucja zwrotna w wysokości 900 zł.\n\nProszę o kontakt telefoniczny pod nr 508 590 539\n(P.S. pracuję w różnych godzinach, więc gdybym nie odebrała, proszę o wiadomość SMS)",
  "meta": {
    "subject": "room",
    "flatMeterage": null,
    "roomMeterage": null,
    "rent": 750,
    "bills": 150,
    "deposit": 900,
    "internetSpeed": null,
    "district": "Krzyki",
    "street": "Armii Krajowej",
    "roomsCount": null,
    "flatmatesCount": null,
    "flatmatesGenders": null,
    "flatmatesOccupation": null,
    "preferredOccupation": null,
    "preferredGender": null
  }
}