{
  "content": "Piękny pokój od zaraz - pierwszy wynajem! Do wynajęcia od zaraz pokój jednoosobowy w mieszkaniu świeżo po kapitalnym remoncie (pierwszy wynajem) o wysokim standardzie na ul. Budziszyńskiej (Nowy Dwór).\n\nW pobliżu:\n\n- Przystanki autobusowe (\"krzyżowka\" na Nowym Dworze): 50 metrów od mieszkania,\n- Lidl: 200 metrów,\n- Netto: 300 metrów,\n- Wrocław Fashion Outlet: 1,1 km,\n- Wrocławki Park Technologiczny: 1 km.\n\nMieszkanie jest jasne, czyste i w pełni umeblowane. W kuchni duża lodówka z zamrażarką, płyta elektryczna, piekarnik, kuchenka mikrofalowa, czajnik oraz pełne wyposażenie - naczynia, garnki, kubki, sztućce i wszystko co potrzebne by zamieszkać.\n\nMieszkanie posiada łazienkę z kabiną prysznicową, WC i umwylką oraz dodatkowe osobne WC z umywalką, co zapewnia komfort użytkowania. Mieszkanie ma 63,3m2 i składa się z 5 pokoi jednoosobowych.\n\nPokój jest w pełni umeblowany - rozkładana wersalka, szafa, komoda, biurko i krzesło. Pokoje zamykane na klucz.\n\nCena za pokój to 730 zł. Dodatkowo stała opłata (ryczałt) za wszystkie rachunki (woda, ogrzewanie, prąd, Internet) w wysokości 160 zł. Szybki internet 300 mbit/s! Umowa do końca września 2019 r. z opcją przedłużenia. Kaucja w wysokości 900 zł.\n\nPokój do zamieszkania od zaraz.\n\nProszę o kontakt pod nr tel. 600 258 823",
  "meta": {
    "subject": "room",
    "flatMeterage": 63.3,
    "roomMeterage": null,
    "rent": 730,
    "bills": 160,
    "deposit": 900,
    "internetSpeed": 300,
    "district": "Nowy Dwór",
    "street": "Budziszyńska",
    "roomsCount": 5,
    "flatmatesCount": null,
    "flatmatesGenders": null,
    "flatmatesOccupation": null,
    "preferredOccupation": null,
    "preferredGender": null
  }
}