{
  "content": "Pokój jednoosobowy ul. Lwowska. Lokalizacja:\nMieszkanie znajdujące się na drugim piętrze w bloku przy ulicy Lwowskiej. Doskonała komunikacja z każdą częścią miasta.\n\nMieszkanie:\n3 pokojowe przeznaczone dla maksymalnie 4 najemców. Przed budynkiem nie ma problemu z miejscami parkingowymi.\n\nDo dyspozycji najemcy:\nUmeblowany pokój w standardzie Ikea zamykany na klucz.\n\nOpłaty\nNajem - 750\nkaucja - 750\nMedia - według zużycia\n(ok. 200 zl za os.)\nWiFi (100mb/s) - gratis\n-\nThere is a clean tidy room available in Lwowska street\n7 minutes from Pereca tram station, 8 minutes by walk to skytower.\n\nEverything you need is available around, shops, biedronka, poczta polska, banks, etc..\n\nFast internet (100 mb), to get your stuff done, as you don`t have to pay for it!, it`s included in the bill (paid by the owner :)\n\nno problem to park a car in the front of bulding\n\nIf interested, please do not hesitate to contact\n\nRegards, ",
  "meta": {
    "subject": "room",
    "flatMeterage": null,
    "roomMeterage": null,
    "rent": 750,
    "bills": 200,
    "deposit": 750,
    "internetSpeed": 100,
    "district": null,
    "street": "Lwowska",
    "roomsCount": 3,
    "flatmatesCount": null,
    "flatmatesGenders": null,
    "flatmatesOccupation": null,
    "preferredOccupation": null,
    "preferredGender": null
  }
}