{
  "content": "Pokój 1 osobowy 14m2 Wrocław Stysia Krzyki kolo Sky Tower Arkady. Witam,\nDuży pokój (ok 14 m2) do wynajęcia od 01 grudnia. Mieszkanie na ul. Stysia - świetna lokalizacja, 20 minut spacerem na Rynek, 15 min na Uniwersytet Ekonomiczny, blisko Sky Tower, Arkady Wrocławskie, Pasaż Zielińskiego. Niedaleko przystanki tramwajowe na Powstańców Śląskich (2,6,7,17,20,24) i Grabiszyńskiej (4,5,11,14). Piętro 4/4\nW mieszkaniu pralka, lodówka, kuchenka gazowa z piekarnikiem, mikrofalówka, odkurzacz. W pokoju duża meblościanka z biurkiem, szafa, rozkładana wersalka, komoda.\nCena: 600 zł + opłata za media (prąd, gaz, cw, zw, co, internet) 150 zł. Razem - 750 zł. Kaucja 850 zł.\nKontakt: sms lub wiadomość prywatna",
  "meta": {
    "subject": "room",
    "flatMeterage": null,
    "roomMeterage": 14,
    "rent": 600,
    "bills": 150,
    "deposit": 750,
    "internetSpeed": null,
    "district": "Krzyki",
    "street": "Stysia",
    "roomsCount": null,
    "flatmatesCount": null,
    "flatmatesGenders": null,
    "flatmatesOccupation": null,
    "preferredOccupation": null,
    "preferredGender": null
  }
}