{
  "content": "Pokój 1-osobowy, Ołbin, Śródmieście, ul. Barlickiego.  POKÓJ:\nUstawny i bardzo jasny pokój o powierzchni 6m2, na rzucie mieszkania oznaczony jako \"pokój nr 1\". Pokój wyposażony w łóżko piętrowe, biurko, krzesło, oraz szafę. Wszystkie meble są nowe. Pokój jest zamykany na klucz.\n\nMIESZKANIE:\nMieszkanie jest 3-pokojowe, rozkładowe z wydzieloną kuchnią, łazienką i WC, zlokalizowane na 4 piętrze kamienicy. Wysoki standard wykończenia, świeżo po remoncie. Pozostałe pokoje 2-osobowe również do wynajęcia. Budynek po generalnym remoncie elewacji, w klatce domofon. W mieszkaniu znajduje się w pełni wyposażona kuchnia: płyta gazowa, piekarnik, lodówka z zamrażarką, czajnik elektryczny, sztućce, naczynia, garnki. W łazience wanna i pralka. Lokal jest w pełni umeblowany. Ogrzewanie gazowe - energooszczędny piec dwufunkcyjny Junkers. Internet UPC 300 megabit.\n\nLOKALIZACJA:\nZnakomite położenie, idealne dla studentów Politechniki, Uniwersytetu Przyrodniczego lub Uniwersytetu Medycznego. 12 minut tramwajem na PWr, UPWr, UM, 5 minut piechotą na Wydział Architektury, 20 minut piechotą na PWr, 20 minut piechotą na Rynek. W okolicy znajdują się Biedronka, Żabka, Dino i piekarnia.\n\nLOKATORZY:\nPokój wyłącznie dla osób niepalących bez zwierząt. Preferowani studenci.\n\nKOSZT:\n650zł/os + opłaty ok. 100-150zł/os przy pięciu osobach w mieszkaniu (woda, prąd, gaz, internet, śmieci).\n\nKAUCJA ZWROTNA:\n700zł/os\n\nCZAS TRWANIA UMOWY:\nUmowa na czas określony z 1-miesięcznym wypowiedzeniem. Pokój dostępny od zaraz.\n\nKONTAKT:\n+48 726 059 795 po 14:00 oraz w weekendy po 12:00. ",
  "meta": {
    "subject": "room",
    "rent": 650,
    "bills": 125,
    "deposit": 700,
    "internetSpeed": 300,
    "district": "Ołbin Śródmieście",
    "street": "Barlickiego",
    "roomsCount": 3,
    "flatmatesCount": null,
    "flatmatesGenders": null,
    "flatmatesOccupation": null,
    "prefferedOccupation": "student",
    "prefferedGender": null
  }
}