{
  "content": "Duży pokój jednoosobowy przy ul. Krakowskiej. Blisko centrum. Do wynajęcia pokój dla jednej osoby w nowym dwupokojowym mieszkaniu o powierzchni 50m2.\n\nPokój ma 16m2. Jest w pełni umeblowany w szafę, biurko z krzesłem, regał, komodę, lampy, rozkładaną wersalkę.\nPokój jest oddzielony do drugiego pokoju kuchnią o powierzchni 9m2.\n\nKuchnia jest zabudowana meblami na wymiar, a dodatkowo znajdują się w niej stół i krzesła.\nJest w pełni wyposażona w zmywarkę, lodówko-zamrażarkę, piekarnik i płytę indukcyjną.\nW łazience znajduje się kabina prysznicowa, WC, umywalka, pralka, regał. W przedpokoju znajduje się szafa wnękowa na wymiar i wieszak na ubrania z ławką i lustrem.\n\nDodatkowo do użytku jest żelazko, deska do prasowania, odkurzacz i czajnik elektryczny.\n\nTeren osiedla jest w pełni zagospodarowany i objęty monitoringiem.\nOsiedle jest pełne zieleni, a w sąsiedztwie znajduje się zalew na rzece Oława.\n\nW mieszkaniu jest ogrzewanie centralne (miejskie), dostęp do wody, energii i internetu.\n\nNa klatce schodowej znajduje się winda. Miesięczny koszt wynajmu pokoju to 900 zł + opłaty za rachunki (w zależności od zużycia) ok. 250 zł (prąd, woda, ogrzewanie, opłaty administracyjne, fundusz remontowy oraz internet).\n\nWymagana jest kaucja zwrotna 1100 zł.\n\nPreferowane są osoby niepalące, lubiące spokój, dbające o czystość, bez zwierząt domowych.\n\nMieszkanie znajduje się na zamkniętym osiedlu, w nowym apartamentowcu z 2017 r.\nLokalizacja: Osiedle \"Krakowskie Tarasy\", ul. Krakowska 84, dojazd do centrum bezpośrednim tramwajem lub autobusem zajmuje tylko 8 minut!\n* 3 minuty do przystanku \"Krakowska\", z którego co chwilę odjeżdżają tramwaje nr 3 i 5, a także autobusy 114 i nocny 243\n* 3 minuty pieszo od galerii handlowej Family Point (siłownia Fitness Academy, supermarket Piotr i Paweł, apteka, bankomat, wszystkie potrzebne sklepy)\n* w pobliżu znajduje się Selgros, Leroy Merlin, stacja paliw, Mc’Donalds, Biedronka. ",
  "meta": {
    "subject": "room",
    "rent": 900,
    "bills": 250,
    "deposit": 1100,
    "internetSpeed": null,
    "district": "Krakowskie Tarasy",
    "street": "Krakowska 84",
    "roomsCount": 2,
    "flatmatesCount": null,
    "flatmatesGenders": null,
    "flatmatesOccupation": null,
    "prefferedOccupation": null,
    "prefferedGender": null
  }
}