{
  "content": "Wygodny pokój ul. Szkocka/Strzegomska. Bardzo ładny, wygodny, słoneczny, wygodny pokój jednoosobowy o pow. 13 m2, zamykany na klucz z dostępem do WiFi. Miejsce spokojne i przygotowane do odpoczynku, nauki i relaksu. .\n\nZdjęcia pokoju poglądowe – trwają ostatnie prace urządzania mieszkania.\n\nDzielnica Muchobór Mały\nAdres Szkocka\n\nLokalizacja\n3 minut do najbliższego przystanku\nBlisko Biedronka 200m,\nFactory 10min. pieszo, IBM. PARK TECHNOLOGICZNY 10min. Pieszo.\n\nKomunikacja\nAutobusy 106, 107, 119, 122, 132, 134, 142, 149, 319, 206, 241, 249\nBudynek\nBlok\nMieszkanie o powierzchni 54 m2\nCzysta klatka schodowa\n\nSzczegóły\nPiętro: 9\nPiwnica: nie\nZwierzęta: nie\nParking: przed budynkiem\nOgrzewanie: miejskie\n\nPomieszczenia\n3 pokoje jednoosobowe\nŁazienka\nToaleta\nKuchnia\nPrzedpokój\n\nWyposażenie i wykończenie\nPokój : szafa, komoda, biurko i łóżko\nKuchnia : kuchenka gazowa, lodówka\nŁazienka : prysznic, pralka\n\nOpłaty 710zł czynsz, 210zł opłaty eksploatacyjne.\nWymagana kaucja w wysokości jednomiesięcznego czynszu 950zł, wolne od 1 grudnia.\n\nZapraszam na prezentację",
  "meta": {
    "subject": "room",
    "rent": 710,
    "bills": 210,
    "deposit": 950,
    "internetSpeed": null,
    "district": "Muchobór Mały",
    "street": "Szkocka",
    "roomsCount": 3,
    "flatmatesCount": null,
    "flatmatesGenders": null,
    "flatmatesOccupation": null,
    "preferredOccupation": null
  }
}