{
  "content": "Ładny pokój jednoosobowy ul.Wyszyńskiego 116 do wynajęcia Wrocław. Do wynajęcia pokój jednoosobowy w mieszkaniu czteropokojowym (czteroosobowym). ŚRÓDMIEŚCIE: ulica Wyszyńskiego 116. Okolica Parku Tołpy. W pobliżu tramwaje 0,1,6,11,23. Autobusy A, N, 128. Trzy przystanki tramwajowe do Placu Grunwaldzkiego.\n\nPokój zamykany na klucz. W pokoju tapczan, szafa, biurko, regał, krzesło.\n\nŁazienka i toaleta razem. W łazience m.in pralka, prysznic.\nKuchnia, w której m.in. mikrofalówka, płyta grzewcza, czajnik elektryczny. Internet: WI-FI.\n\nOgrzewanie poprzez bezobsługowy piec gazowy dwufunkcyjny (ciepła woda użytkowa, centralne ogrzewanie).\n\nCzynsz: 750 PLN + gaz, woda, prąd wg liczników (około 100PLN na osobę na miesiąc – w zimie więcej, latem mniej).\nInternet gratis.\n\nKaucja: 800 PLN płatna z góry.\n\nPokój wynajmowany bezpośrednio przez właściciela. Do wynajęcia od zaraz.\n\ntel kontaktowy 511 959 300",
  "meta": {
    "subject": "room",
    "flatMeterage": null,
    "roomMeterage": null,
    "rent": 750,
    "bills": 100,
    "deposit": 800,
    "internetSpeed": null,
    "district": "Śródmieście",
    "street": "Wyszyńskiego 116",
    "roomsCount": 4,
    "flatmatesCount": 3,
    "flatmatesGenders": null,
    "flatmatesOccupation": null,
    "preferredOccupation": null,
    "preferredGender": null
  }
}