{
  "content": "Pokój jednoosobowy -nowoczesne osiedle - Wrocław- Brochów. Szukam lokatora do jednego pokoju do mieszkania 2- pokojowego 51m/kw na drugim piętrze w 3-piętrowym budynku. Pokój umeblowany (szafa, sofa, stolik, komoda, krzesła, fotel) o wielkości 12,5 m?kw.\nMieszkanie znajduje się w nowym bloku - 2018 r w cichej dzielnicy przy ul. Mościckiego.\nMieszkanie słoneczne, o wysokim standardzie - winda, prywatny parking.\nOkna nie wychodzą na ulicę także nie ma hałasu.\nKuchnia i łazienka w pełni wyposażone: kuchenka, lodówka, zmywarka, mikrofala (nowe sprzęty )\nCzynsz 1000 zł + 200 zł opłaty. Kaucja zwrotna 1200 zł.\nMieszkanie dostępne od zaraz. Preferowane ciche i spokojne osoby niepalące. Kontakt telefoniczny 792-436-475",
  "meta": {
    "subject": "room",
    "flatMeterage": 51,
    "roomMeterage": 12.5,
    "rent": 1000,
    "bills": 200,
    "deposit": 1200,
    "internetSpeed": null,
    "district": "Brochów",
    "street": "Mościckiego",
    "roomsCount": 2,
    "flatmatesCount": null,
    "flatmatesGenders": null,
    "flatmatesOccupation": null,
    "preferredOccupation": null,
    "preferredGender": null
  }
}